karp/lex_core/__init__.py
karp/lex_core/py.typed
karp/lex_core/commands/__init__.py
karp/lex_core/dtos/__init__.py
karp/lex_core/value_objects/__init__.py
karp_lex_core-0.6.3.dist-info/METADATA
karp_lex_core-0.6.3.dist-info/WHEEL
karp_lex_core-0.6.3.dist-info/licenses/LICENSE
karp_lex_core-0.6.3.dist-info/RECORD
